{
  "data": {
    "p2p": {
      "Sunflower": 0.0003745,
      "Potato": 0.0003745,
      "Pumpkin": 0.00095,
      "Carrot": 0.002093,
      "Cabbage": 0.0022225,
      "Beetroot": 0.006098,
      "Cauliflower": 0.008894,
      "Parsnip": 0.01419,
      "Radish": 0.01355294,
      "Wheat": 0.01624923,
      "Kale": 0.02051928,
      "Apple": 0.027698,
      "Blueberry": 0.01956941,
      "Orange": 0.02166,
      "Eggplant": 0.0123,
      "Corn": 0.01575,
      "Banana": 0.02844621,
      "Soybean": 0.00275,
      "Grape": 0.295,
      "Rice": 0.355,
      "Olive": 0.44376,
      "Tomato": 0.005083,
      "Lemon": 0.0119,
      "Barley": 0.02898,
      "Rhubarb": 0.00077486,
      "Zucchini": 0.000625,
      "Yam": 0.0031624,
      "Broccoli": 0.0048598,
      "Pepper": 0.0066,
      "Onion": 0.0139,
      "Turnip": 0.0171,
      "Artichoke": 0.014004,
      "Duskberry": 1.1111,
      "Lunara": 0.5596,
      "Celestine": 0.2193,
      "Wood": 0.015003,
      "Stone": 0.027,
      "Iron": 0.09816,
      "Gold": 0.35336,
      "Egg": 0.021,
      "Honey": 0.1481,
      "Crimstone": 0.793,
      "Leather": 0.09948,
      "Wool": 0.052465,
      "Merino Wool": 0.01522,
      "Feather": 0.010287,
      "Milk": 0.12894,
      "Obsidian": 19.5,
      "Salt": 0.00448733,
      "Goblin Emblem": 0.071499,
      "Bumpkin Emblem": 0.086599,
      "Sunflorian Emblem": 0.08798,
      "Nightshade Emblem": 0.06485,
      "Ruffroot": 0.4297,
      "Chewed Bone": 0.4194,
      "Heart Leaf": 0.4144,
      "Moonfur": 3.41666667,
      "Ribbon": 0.408,
      "Dewberry": 0.4477,
      "Wild Grass": 0.433,
      "Frost Pebble": 0.41268,
      "Capsule Bait": 0.01974,
      "Umbrella Bait": 0.0353,
      "Crimson Baitfish": 0.04798
    },
    "seq": {},
    "ge": {}
  },
  "updatedAt": 1782703805506,
  "updated_text": "7 minutes ago"
}