{
  "data": {
    "p2p": {
      "Sunflower": 0.00023662,
      "Potato": 0.00032553,
      "Pumpkin": 0.00107745,
      "Carrot": 0.00204345,
      "Cabbage": 0.00190633,
      "Beetroot": 0.005957,
      "Cauliflower": 0.00725905,
      "Parsnip": 0.015764,
      "Radish": 0.008496,
      "Wheat": 0.012,
      "Kale": 0.0189,
      "Apple": 0.02238,
      "Blueberry": 0.013,
      "Orange": 0.014795,
      "Eggplant": 0.00754,
      "Corn": 0.01847899,
      "Banana": 0.0203,
      "Soybean": 0.00239171,
      "Grape": 0.2842,
      "Rice": 0.35885,
      "Olive": 0.49988,
      "Tomato": 0.00484567,
      "Lemon": 0.010055,
      "Barley": 0.027596,
      "Rhubarb": 0.00038,
      "Zucchini": 0.000466,
      "Yam": 0.0026975,
      "Broccoli": 0.003176,
      "Pepper": 0.005659,
      "Onion": 0.0109985,
      "Turnip": 0.00847231,
      "Artichoke": 0.0124,
      "Duskberry": 0.9111,
      "Lunara": 0.4547,
      "Celestine": 0.18148,
      "Wood": 0.0096548,
      "Stone": 0.01893333,
      "Iron": 0.05578167,
      "Gold": 0.2238,
      "Egg": 0.02320339,
      "Honey": 0.0593,
      "Crimstone": 0.55481667,
      "Leather": 0.12266538,
      "Wool": 0.06232,
      "Merino Wool": 0.01,
      "Feather": 0.00426667,
      "Milk": 0.092876,
      "Obsidian": 22.8899,
      "Goblin Emblem": 0.05889231,
      "Bumpkin Emblem": 0.065963,
      "Sunflorian Emblem": 0.048595,
      "Nightshade Emblem": 0.0525,
      "Ruffroot": 0.6998,
      "Chewed Bone": 0.688,
      "Heart leaf": 0.6455,
      "Moonfur": 3.1415,
      "Ribbon": 0.5999,
      "Dewberry": 0.6848,
      "Wild Grass": 0.73,
      "Frost Pebble": 0.6908
    },
    "seq": {},
    "ge": {}
  },
  "updatedAt": 1766772905117,
  "updated_text": "5 minutes ago"
}