{
  "data": {
    "p2p": {
      "Sunflower": 0.0002674,
      "Potato": 0.0003,
      "Pumpkin": 0.00083545,
      "Carrot": 0.001642,
      "Cabbage": 0.003388,
      "Beetroot": 0.0069996,
      "Cauliflower": 0.01022199,
      "Parsnip": 0.01538333,
      "Radish": 0.0082,
      "Wheat": 0.0154375,
      "Kale": 0.0192,
      "Apple": 0.02747273,
      "Blueberry": 0.01852,
      "Orange": 0.0186,
      "Eggplant": 0.0072,
      "Corn": 0.0194497,
      "Banana": 0.0195,
      "Soybean": 0.003392,
      "Grape": 0.273,
      "Rice": 0.3555,
      "Olive": 0.45833333,
      "Tomato": 0.005048,
      "Lemon": 0.009,
      "Barley": 0.02603175,
      "Rhubarb": 0.00042945,
      "Zucchini": 0.000402,
      "Yam": 0.00297493,
      "Broccoli": 0.003501,
      "Pepper": 0.004,
      "Onion": 0.00995516,
      "Turnip": 0.0086,
      "Artichoke": 0.01385,
      "Duskberry": 0.93,
      "Lunara": 0.457,
      "Celestine": 0.174885,
      "Wood": 0.00938,
      "Stone": 0.01845,
      "Iron": 0.0602,
      "Gold": 0.243258,
      "Egg": 0.027994,
      "Honey": 0.0688,
      "Crimstone": 0.56098,
      "Leather": 0.1427,
      "Wool": 0.0605,
      "Merino Wool": 0.01,
      "Feather": 0.0037,
      "Milk": 0.09461429,
      "Obsidian": 21.99,
      "Goblin Emblem": 0.057994,
      "Bumpkin Emblem": 0.07429333,
      "Sunflorian Emblem": 0.055712,
      "Nightshade Emblem": 0.0599895,
      "Ruffroot": 0.7073,
      "Chewed Bone": 0.7,
      "Heart leaf": 0.636,
      "Moonfur": 3,
      "Ribbon": 0.69,
      "Dewberry": 0.6445,
      "Wild Grass": 0.69,
      "Frost Pebble": 0.6985
    },
    "seq": {},
    "ge": {}
  },
  "updatedAt": 1767231007240,
  "updated_text": "10 minutes ago"
}