{
  "data": {
    "p2p": {
      "Sunflower": 0.00028186,
      "Potato": 0.0004593,
      "Pumpkin": 0.00112,
      "Carrot": 0.0019999,
      "Cabbage": 0.00167368,
      "Beetroot": 0.0052646,
      "Cauliflower": 0.007168,
      "Parsnip": 0.012802,
      "Radish": 0.010199,
      "Wheat": 0.01338667,
      "Kale": 0.0175675,
      "Apple": 0.024156,
      "Blueberry": 0.01298833,
      "Orange": 0.019865,
      "Eggplant": 0.009592,
      "Corn": 0.0232,
      "Banana": 0.023838,
      "Soybean": 0.0024,
      "Grape": 0.3385,
      "Rice": 0.34,
      "Olive": 0.52,
      "Tomato": 0.0057955,
      "Lemon": 0.0095,
      "Barley": 0.0266,
      "Rhubarb": 0.0006,
      "Zucchini": 0.0005,
      "Yam": 0.00247485,
      "Broccoli": 0.002993,
      "Pepper": 0.003583,
      "Onion": 0.010708,
      "Turnip": 0.010938,
      "Artichoke": 0.0126,
      "Duskberry": 0.95,
      "Lunara": 0.4739375,
      "Celestine": 0.184,
      "Wood": 0.010193,
      "Stone": 0.0199575,
      "Iron": 0.07094,
      "Gold": 0.27,
      "Egg": 0.02385897,
      "Honey": 0.07969565,
      "Crimstone": 0.64444444,
      "Leather": 0.13,
      "Wool": 0.088,
      "Merino Wool": 0.02655,
      "Feather": 0.0083,
      "Milk": 0.12,
      "Obsidian": 37.9,
      "Goblin Emblem": 0.06345,
      "Bumpkin Emblem": 0.07,
      "Sunflorian Emblem": 0.0559995,
      "Nightshade Emblem": 0.053,
      "Ruffroot": 1.041,
      "Chewed Bone": 1.39,
      "Heart leaf": 1,
      "Moonfur": 4.185,
      "Ribbon": 1.1498,
      "Dewberry": 1.195,
      "Wild Grass": 1.14,
      "Frost Pebble": 1.019
    },
    "seq": {},
    "ge": {}
  },
  "updatedAt": 1763295305017,
  "updated_text": "10 minutes ago"
}