{
  "data": {
    "p2p": {
      "Sunflower": 0.000257,
      "Potato": 0.0003,
      "Pumpkin": 0.000771,
      "Carrot": 0.0019,
      "Cabbage": 0.001877,
      "Beetroot": 0.0052,
      "Cauliflower": 0.00929369,
      "Parsnip": 0.01498,
      "Radish": 0.0106,
      "Wheat": 0.01894538,
      "Kale": 0.0288,
      "Apple": 0.0275,
      "Blueberry": 0.02047432,
      "Orange": 0.0191925,
      "Eggplant": 0.00889077,
      "Corn": 0.0256465,
      "Banana": 0.02813019,
      "Soybean": 0.00270554,
      "Grape": 0.2956,
      "Rice": 0.44184,
      "Olive": 0.48827,
      "Tomato": 0.005024,
      "Lemon": 0.01469,
      "Barley": 0.0367,
      "Rhubarb": 0.000512,
      "Zucchini": 0.00078919,
      "Yam": 0.002609,
      "Broccoli": 0.002795,
      "Pepper": 0.00598083,
      "Onion": 0.01316333,
      "Turnip": 0.0102275,
      "Artichoke": 0.0153748,
      "Duskberry": 1.21,
      "Lunara": 0.55825,
      "Celestine": 0.22173,
      "Wood": 0.011189,
      "Stone": 0.022898,
      "Iron": 0.0677,
      "Gold": 0.25,
      "Egg": 0.03,
      "Honey": 0.08007778,
      "Crimstone": 0.7105,
      "Leather": 0.15066667,
      "Wool": 0.0737,
      "Merino Wool": 0.0115,
      "Feather": 0.00806,
      "Milk": 0.16973333,
      "Obsidian": 21.98,
      "Goblin Emblem": 0.062985,
      "Bumpkin Emblem": 0.0775,
      "Sunflorian Emblem": 0.05919,
      "Nightshade Emblem": 0.0699,
      "Ruffroot": 0.78,
      "Chewed Bone": 0.7963,
      "Heart Leaf": 0.7799,
      "Moonfur": 4.979,
      "Ribbon": 0.7799,
      "Dewberry": 0.75,
      "Wild Grass": 0.812,
      "Frost Pebble": 0.7957
    },
    "seq": {},
    "ge": {}
  },
  "updatedAt": 1774074606545,
  "updated_text": "4 minutes ago"
}