{
  "data": {
    "p2p": {
      "Sunflower": 0.00027247,
      "Potato": 0.00030333,
      "Pumpkin": 0.0008014,
      "Carrot": 0.001955,
      "Cabbage": 0.0026108,
      "Beetroot": 0.006393,
      "Cauliflower": 0.01104,
      "Parsnip": 0.01756657,
      "Radish": 0.009392,
      "Wheat": 0.014594,
      "Kale": 0.023,
      "Apple": 0.0190293,
      "Blueberry": 0.01865,
      "Orange": 0.01434,
      "Eggplant": 0.0081,
      "Corn": 0.019,
      "Banana": 0.01752774,
      "Soybean": 0.002198,
      "Grape": 0.24842,
      "Rice": 0.3375,
      "Olive": 0.4304,
      "Tomato": 0.004597,
      "Lemon": 0.009598,
      "Barley": 0.02255667,
      "Rhubarb": 0.0004476,
      "Zucchini": 0.00048662,
      "Yam": 0.00287375,
      "Broccoli": 0.003032,
      "Pepper": 0.004702,
      "Onion": 0.010994,
      "Turnip": 0.01,
      "Artichoke": 0.0097,
      "Duskberry": 0.786,
      "Lunara": 0.3896,
      "Celestine": 0.155,
      "Wood": 0.00913319,
      "Stone": 0.016,
      "Iron": 0.06396346,
      "Gold": 0.245,
      "Egg": 0.02449,
      "Honey": 0.06318182,
      "Crimstone": 0.52895,
      "Leather": 0.119798,
      "Wool": 0.05884,
      "Merino Wool": 0.0127,
      "Feather": 0.00568387,
      "Milk": 0.129672,
      "Obsidian": 21.3997,
      "Goblin Emblem": 0.0589995,
      "Bumpkin Emblem": 0.077949,
      "Sunflorian Emblem": 0.054896,
      "Nightshade Emblem": 0.06179,
      "Ruffroot": 0.51,
      "Chewed Bone": 0.5193,
      "Heart leaf": 0.504,
      "Moonfur": 3.009,
      "Ribbon": 0.48996,
      "Dewberry": 0.5189,
      "Wild Grass": 0.5185,
      "Frost Pebble": 0.5148
    },
    "seq": {},
    "ge": {}
  },
  "updatedAt": 1769911618892,
  "updated_text": "2 minutes ago"
}