{
  "data": {
    "p2p": {
      "Sunflower": 0.00023875,
      "Potato": 0.0005232,
      "Pumpkin": 0.00129565,
      "Carrot": 0.00192585,
      "Cabbage": 0.001796,
      "Beetroot": 0.0059999,
      "Cauliflower": 0.007,
      "Parsnip": 0.012378,
      "Radish": 0.01303046,
      "Wheat": 0.0131772,
      "Kale": 0.01999,
      "Apple": 0.0246,
      "Blueberry": 0.013832,
      "Orange": 0.01764333,
      "Eggplant": 0.01007991,
      "Corn": 0.01904191,
      "Banana": 0.025092,
      "Soybean": 0.00262788,
      "Grape": 0.35552857,
      "Rice": 0.3833,
      "Olive": 0.59,
      "Tomato": 0.00591036,
      "Lemon": 0.010756,
      "Barley": 0.02406667,
      "Rhubarb": 0.000664,
      "Zucchini": 0.000476,
      "Yam": 0.00247238,
      "Broccoli": 0.002599,
      "Pepper": 0.00387861,
      "Onion": 0.0108,
      "Turnip": 0.00877789,
      "Artichoke": 0.0124,
      "Duskberry": 1.01,
      "Lunara": 0.4996,
      "Celestine": 0.19966,
      "Wood": 0.0102,
      "Stone": 0.0195,
      "Iron": 0.072035,
      "Gold": 0.2743,
      "Egg": 0.025035,
      "Honey": 0.075,
      "Crimstone": 0.658,
      "Leather": 0.15558,
      "Wool": 0.07799667,
      "Merino Wool": 0.01741111,
      "Feather": 0.00795581,
      "Milk": 0.11954,
      "Obsidian": 33.2,
      "Goblin Emblem": 0.072648,
      "Bumpkin Emblem": 0.064495,
      "Sunflorian Emblem": 0.0598,
      "Nightshade Emblem": 0.049748,
      "Ruffroot": 1.09996667,
      "Chewed Bone": 1.2399,
      "Heart leaf": 0.999,
      "Moonfur": 3.9633,
      "Ribbon": 1.055,
      "Dewberry": 1.097,
      "Wild Grass": 1.16666667,
      "Frost Pebble": 1.2017
    },
    "seq": {},
    "ge": {}
  },
  "updatedAt": 1763705704539,
  "updated_text": "6 minutes ago"
}