{
  "data": {
    "p2p": {
      "Sunflower": 0.00027,
      "Potato": 0.00030467,
      "Pumpkin": 0.00089495,
      "Carrot": 0.002,
      "Cabbage": 0.003287,
      "Beetroot": 0.00661099,
      "Cauliflower": 0.00926043,
      "Parsnip": 0.01563707,
      "Radish": 0.01082974,
      "Wheat": 0.0126,
      "Kale": 0.016664,
      "Apple": 0.02107603,
      "Blueberry": 0.01647059,
      "Orange": 0.016985,
      "Eggplant": 0.0089832,
      "Corn": 0.0218,
      "Banana": 0.0206,
      "Soybean": 0.00277201,
      "Grape": 0.4895625,
      "Rice": 0.35135135,
      "Olive": 0.61341,
      "Tomato": 0.004875,
      "Lemon": 0.0103,
      "Barley": 0.02189593,
      "Rhubarb": 0.000525,
      "Zucchini": 0.0004975,
      "Yam": 0.00262,
      "Broccoli": 0.00289697,
      "Pepper": 0.004056,
      "Onion": 0.013899,
      "Turnip": 0.01193333,
      "Artichoke": 0.01130933,
      "Duskberry": 0.85,
      "Lunara": 0.425,
      "Celestine": 0.1735125,
      "Wood": 0.01004,
      "Stone": 0.01937267,
      "Iron": 0.06683,
      "Gold": 0.2517,
      "Egg": 0.02300494,
      "Honey": 0.0608,
      "Crimstone": 0.57142,
      "Leather": 0.1333,
      "Wool": 0.0675,
      "Merino Wool": 0.011693,
      "Feather": 0.00591259,
      "Milk": 0.1017,
      "Obsidian": 25.5,
      "Goblin Emblem": 0.059428,
      "Bumpkin Emblem": 0.07118,
      "Sunflorian Emblem": 0.05695,
      "Nightshade Emblem": 0.0538,
      "Ruffroot": 0.7636,
      "Chewed Bone": 0.73,
      "Heart leaf": 0.64633333,
      "Moonfur": 2.554,
      "Ribbon": 0.7,
      "Dewberry": 0.728,
      "Wild Grass": 0.775,
      "Frost Pebble": 0.8089
    },
    "seq": {},
    "ge": {}
  },
  "updatedAt": 1765369806025,
  "updated_text": "10 minutes ago"
}