{
  "data": {
    "p2p": {
      "Sunflower": 0.00029163,
      "Potato": 0.00063925,
      "Pumpkin": 0.00129495,
      "Carrot": 0.002196,
      "Cabbage": 0.00183829,
      "Beetroot": 0.006206,
      "Cauliflower": 0.007296,
      "Parsnip": 0.01249545,
      "Radish": 0.01215,
      "Wheat": 0.01357333,
      "Kale": 0.0197,
      "Apple": 0.025,
      "Blueberry": 0.012085,
      "Orange": 0.018646,
      "Eggplant": 0.0100964,
      "Corn": 0.01927,
      "Banana": 0.024888,
      "Soybean": 0.00268,
      "Grape": 0.3516,
      "Rice": 0.344385,
      "Olive": 0.5817,
      "Tomato": 0.0048735,
      "Lemon": 0.01175,
      "Barley": 0.025718,
      "Rhubarb": 0.0006661,
      "Zucchini": 0.00050025,
      "Yam": 0.00249,
      "Broccoli": 0.002894,
      "Pepper": 0.004297,
      "Onion": 0.0106,
      "Turnip": 0.00866,
      "Artichoke": 0.012799,
      "Duskberry": 1.075,
      "Lunara": 0.5,
      "Celestine": 0.19996667,
      "Wood": 0.01027857,
      "Stone": 0.019132,
      "Iron": 0.07283871,
      "Gold": 0.26653333,
      "Egg": 0.02398,
      "Honey": 0.0804,
      "Crimstone": 0.66935,
      "Leather": 0.14290769,
      "Wool": 0.07207,
      "Merino Wool": 0.01377,
      "Feather": 0.007295,
      "Milk": 0.11088654,
      "Obsidian": 36.84,
      "Goblin Emblem": 0.064944,
      "Bumpkin Emblem": 0.063975,
      "Sunflorian Emblem": 0.059999,
      "Nightshade Emblem": 0.049687,
      "Ruffroot": 1.1289,
      "Chewed Bone": 1.09,
      "Heart leaf": 1.004,
      "Moonfur": 3.5166,
      "Ribbon": 1.0937,
      "Dewberry": 1.029,
      "Wild Grass": 1.0999,
      "Frost Pebble": 1.036
    },
    "seq": {},
    "ge": {}
  },
  "updatedAt": 1763921705843,
  "updated_text": "2 minutes ago"
}