{
  "data": {
    "p2p": {
      "Sunflower": 0.00026673,
      "Potato": 0.0003871,
      "Pumpkin": 0.00099471,
      "Carrot": 0.0018906,
      "Cabbage": 0.0027,
      "Beetroot": 0.008232,
      "Cauliflower": 0.009,
      "Parsnip": 0.017196,
      "Radish": 0.01048,
      "Wheat": 0.012309,
      "Kale": 0.02098,
      "Apple": 0.02679643,
      "Blueberry": 0.01399,
      "Orange": 0.016478,
      "Eggplant": 0.00857833,
      "Corn": 0.02149836,
      "Banana": 0.0208,
      "Soybean": 0.0024,
      "Grape": 0.367,
      "Rice": 0.38995909,
      "Olive": 0.59375,
      "Tomato": 0.00601,
      "Lemon": 0.009976,
      "Barley": 0.0248,
      "Rhubarb": 0.0004925,
      "Zucchini": 0.0004844,
      "Yam": 0.003305,
      "Broccoli": 0.00374412,
      "Pepper": 0.003858,
      "Onion": 0.01095,
      "Turnip": 0.0091,
      "Artichoke": 0.0172,
      "Duskberry": 1.101,
      "Lunara": 0.5085,
      "Celestine": 0.18555,
      "Wood": 0.01024,
      "Stone": 0.019148,
      "Iron": 0.0723,
      "Gold": 0.258,
      "Egg": 0.0266,
      "Honey": 0.07015714,
      "Crimstone": 0.5995,
      "Leather": 0.14841,
      "Wool": 0.06234,
      "Merino Wool": 0.01299636,
      "Feather": 0.006948,
      "Milk": 0.11838333,
      "Obsidian": 29.9,
      "Goblin Emblem": 0.063,
      "Bumpkin Emblem": 0.0705,
      "Sunflorian Emblem": 0.061465,
      "Nightshade Emblem": 0.04345,
      "Ruffroot": 0.81,
      "Chewed Bone": 0.84993333,
      "Heart leaf": 0.75,
      "Moonfur": 3,
      "Ribbon": 0.825,
      "Dewberry": 0.824,
      "Wild Grass": 0.8,
      "Frost Pebble": 0.7767
    },
    "seq": {},
    "ge": {}
  },
  "updatedAt": 1764785706558,
  "updated_text": "5 minutes ago"
}