{
  "data": {
    "p2p": {
      "Sunflower": 0.0003476,
      "Potato": 0.0005253,
      "Pumpkin": 0.00105,
      "Carrot": 0.00215067,
      "Cabbage": 0.001798,
      "Beetroot": 0.005898,
      "Cauliflower": 0.009061,
      "Parsnip": 0.0125,
      "Radish": 0.01106482,
      "Wheat": 0.018789,
      "Kale": 0.02184874,
      "Apple": 0.0235,
      "Blueberry": 0.0198,
      "Orange": 0.01812,
      "Eggplant": 0.01077871,
      "Corn": 0.018,
      "Banana": 0.02427,
      "Soybean": 0.0025478,
      "Grape": 0.2596,
      "Rice": 0.3666625,
      "Olive": 0.40571429,
      "Tomato": 0.00522333,
      "Lemon": 0.013,
      "Barley": 0.029488,
      "Rhubarb": 0.000659,
      "Zucchini": 0.0005996,
      "Yam": 0.0027774,
      "Broccoli": 0.00345614,
      "Pepper": 0.005986,
      "Onion": 0.01334,
      "Turnip": 0.011292,
      "Artichoke": 0.0139,
      "Duskberry": 0.93395,
      "Lunara": 0.47,
      "Celestine": 0.191225,
      "Wood": 0.013547,
      "Stone": 0.02157885,
      "Iron": 0.0788,
      "Gold": 0.43626667,
      "Egg": 0.0213,
      "Honey": 0.091,
      "Crimstone": 0.6,
      "Leather": 0.14777778,
      "Wool": 0.0667,
      "Merino Wool": 0.012798,
      "Feather": 0.008,
      "Milk": 0.14298,
      "Obsidian": 16.999,
      "Salt": 0.03171429,
      "Goblin Emblem": 0.06525,
      "Bumpkin Emblem": 0.08632,
      "Sunflorian Emblem": 0.0599,
      "Nightshade Emblem": 0.04998,
      "Ruffroot": 0.5595,
      "Chewed Bone": 0.54,
      "Heart Leaf": 0.549,
      "Moonfur": 4.3288,
      "Ribbon": 0.55,
      "Dewberry": 0.55,
      "Wild Grass": 0.54,
      "Frost Pebble": 0.545
    },
    "seq": {},
    "ge": {}
  },
  "updatedAt": 1777988707542,
  "updated_text": "2 minutes ago"
}