{
  "data": {
    "p2p": {
      "Sunflower": 0.00034975,
      "Potato": 0.0003,
      "Pumpkin": 0.00095,
      "Carrot": 0.00215,
      "Cabbage": 0.00184,
      "Beetroot": 0.0058,
      "Cauliflower": 0.00977965,
      "Parsnip": 0.0155486,
      "Radish": 0.0106196,
      "Wheat": 0.0138878,
      "Kale": 0.02387,
      "Apple": 0.025092,
      "Blueberry": 0.01899375,
      "Orange": 0.01699667,
      "Eggplant": 0.0093,
      "Corn": 0.01466,
      "Banana": 0.02392857,
      "Soybean": 0.00269,
      "Grape": 0.2701,
      "Rice": 0.33998125,
      "Olive": 0.395,
      "Tomato": 0.00499333,
      "Lemon": 0.009904,
      "Barley": 0.02948,
      "Rhubarb": 0.00075,
      "Zucchini": 0.000866,
      "Yam": 0.003575,
      "Broccoli": 0.005875,
      "Pepper": 0.006016,
      "Onion": 0.01367778,
      "Turnip": 0.01368,
      "Artichoke": 0.016,
      "Duskberry": 0.92873333,
      "Lunara": 0.46962,
      "Celestine": 0.18862,
      "Wood": 0.0141755,
      "Stone": 0.0275,
      "Iron": 0.09698333,
      "Gold": 0.35666471,
      "Egg": 0.02274333,
      "Honey": 0.11747273,
      "Crimstone": 0.745,
      "Leather": 0.09729167,
      "Wool": 0.043744,
      "Merino Wool": 0.011742,
      "Feather": 0.0094868,
      "Milk": 0.10121,
      "Obsidian": 18.4,
      "Salt": 0.0043,
      "Goblin Emblem": 0.073314,
      "Bumpkin Emblem": 0.0838,
      "Sunflorian Emblem": 0.078997,
      "Nightshade Emblem": 0.06848,
      "Ruffroot": 0.444,
      "Chewed Bone": 0.4497,
      "Heart Leaf": 0.41996364,
      "Moonfur": 3.8472,
      "Ribbon": 0.4436,
      "Dewberry": 0.4489,
      "Wild Grass": 0.454,
      "Frost Pebble": 0.4303,
      "Capsule Bait": 0.0179,
      "Umbrella Bait": 0.0413,
      "Crimson Baitfish": 0.03748
    },
    "seq": {},
    "ge": {}
  },
  "updatedAt": 1783909805761,
  "updated_text": "3 minutes ago"
}