{
  "data": {
    "p2p": {
      "Sunflower": 0.00042123,
      "Potato": 0.00041667,
      "Pumpkin": 0.001078,
      "Carrot": 0.00204995,
      "Cabbage": 0.00193785,
      "Beetroot": 0.006294,
      "Cauliflower": 0.009294,
      "Parsnip": 0.014,
      "Radish": 0.01048824,
      "Wheat": 0.017439,
      "Kale": 0.023,
      "Apple": 0.025915,
      "Blueberry": 0.0191,
      "Orange": 0.01974978,
      "Eggplant": 0.01046333,
      "Corn": 0.01795733,
      "Banana": 0.0248,
      "Soybean": 0.00268,
      "Grape": 0.289,
      "Rice": 0.396,
      "Olive": 0.41175714,
      "Tomato": 0.004994,
      "Lemon": 0.0138,
      "Barley": 0.03132,
      "Rhubarb": 0.0005764,
      "Zucchini": 0.00077933,
      "Yam": 0.002887,
      "Broccoli": 0.004154,
      "Pepper": 0.007859,
      "Onion": 0.0148,
      "Turnip": 0.012348,
      "Artichoke": 0.0158,
      "Duskberry": 0.9,
      "Lunara": 0.49221,
      "Celestine": 0.1939,
      "Wood": 0.017273,
      "Stone": 0.0251275,
      "Iron": 0.079976,
      "Gold": 0.3912,
      "Egg": 0.026,
      "Honey": 0.095,
      "Crimstone": 0.63456667,
      "Leather": 0.12915556,
      "Wool": 0.0664,
      "Merino Wool": 0.012935,
      "Feather": 0.008666,
      "Milk": 0.148,
      "Obsidian": 19.5,
      "Salt": 0.00638,
      "Goblin Emblem": 0.06,
      "Bumpkin Emblem": 0.075,
      "Sunflorian Emblem": 0.072,
      "Nightshade Emblem": 0.061,
      "Ruffroot": 0.448,
      "Chewed Bone": 0.43589744,
      "Heart Leaf": 0.43453333,
      "Moonfur": 3.785,
      "Ribbon": 0.438,
      "Dewberry": 0.48,
      "Wild Grass": 0.421,
      "Frost Pebble": 0.4148,
      "Capsule Bait": 0.0261,
      "Umbrella Bait": 0.03738,
      "Crimson Baitfish": 0.0609
    },
    "seq": {},
    "ge": {}
  },
  "updatedAt": 1778833808999,
  "updated_text": "10 minutes ago"
}