{
  "data": {
    "p2p": {
      "Sunflower": 0.00034995,
      "Potato": 0.00030673,
      "Pumpkin": 0.000989,
      "Carrot": 0.002,
      "Cabbage": 0.001872,
      "Beetroot": 0.0056,
      "Cauliflower": 0.00899333,
      "Parsnip": 0.015555,
      "Radish": 0.0098,
      "Wheat": 0.013975,
      "Kale": 0.0223,
      "Apple": 0.02428925,
      "Blueberry": 0.01698889,
      "Orange": 0.0173,
      "Eggplant": 0.01033095,
      "Corn": 0.014899,
      "Banana": 0.0242,
      "Soybean": 0.00244478,
      "Grape": 0.2742,
      "Rice": 0.33998,
      "Olive": 0.39846667,
      "Tomato": 0.004994,
      "Lemon": 0.0095375,
      "Barley": 0.0294845,
      "Rhubarb": 0.00077395,
      "Zucchini": 0.00082395,
      "Yam": 0.003346,
      "Broccoli": 0.005096,
      "Pepper": 0.007104,
      "Onion": 0.01370952,
      "Turnip": 0.0136,
      "Artichoke": 0.015,
      "Duskberry": 0.94726667,
      "Lunara": 0.465,
      "Celestine": 0.18995,
      "Wood": 0.014338,
      "Stone": 0.027498,
      "Iron": 0.0969,
      "Gold": 0.35766667,
      "Egg": 0.02084884,
      "Honey": 0.1045,
      "Crimstone": 0.7499,
      "Leather": 0.096,
      "Wool": 0.04428,
      "Merino Wool": 0.012,
      "Feather": 0.01003846,
      "Milk": 0.101778,
      "Obsidian": 18.8009,
      "Salt": 0.004,
      "Goblin Emblem": 0.065,
      "Bumpkin Emblem": 0.084,
      "Sunflorian Emblem": 0.078998,
      "Nightshade Emblem": 0.0579765,
      "Ruffroot": 0.4199,
      "Chewed Bone": 0.45,
      "Heart Leaf": 0.41666667,
      "Moonfur": 3.71428571,
      "Ribbon": 0.40666667,
      "Dewberry": 0.42,
      "Wild Grass": 0.41995,
      "Frost Pebble": 0.4301,
      "Capsule Bait": 0.019,
      "Umbrella Bait": 0.0428,
      "Crimson Baitfish": 0.03976
    },
    "seq": {},
    "ge": {}
  },
  "updatedAt": 1783861684186,
  "updated_text": "a minute ago"
}