{
  "data": {
    "p2p": {
      "Sunflower": 0.00029975,
      "Potato": 0.0003718,
      "Pumpkin": 0.00084895,
      "Carrot": 0.001966,
      "Cabbage": 0.002005,
      "Beetroot": 0.00569288,
      "Cauliflower": 0.01,
      "Parsnip": 0.01314788,
      "Radish": 0.01248382,
      "Wheat": 0.0228,
      "Kale": 0.02457667,
      "Apple": 0.02817391,
      "Blueberry": 0.02891277,
      "Orange": 0.0212,
      "Eggplant": 0.0102766,
      "Corn": 0.0298998,
      "Banana": 0.02796,
      "Soybean": 0.00295933,
      "Grape": 0.30585882,
      "Rice": 0.40536,
      "Olive": 0.49718,
      "Tomato": 0.0054,
      "Lemon": 0.018191,
      "Barley": 0.03225,
      "Rhubarb": 0.0005945,
      "Zucchini": 0.0006173,
      "Yam": 0.002595,
      "Broccoli": 0.0027905,
      "Pepper": 0.005698,
      "Onion": 0.01475,
      "Turnip": 0.015732,
      "Artichoke": 0.0162,
      "Duskberry": 1.17,
      "Lunara": 0.564,
      "Celestine": 0.229,
      "Wood": 0.01240956,
      "Stone": 0.02099535,
      "Iron": 0.0727,
      "Gold": 0.296,
      "Egg": 0.02848889,
      "Honey": 0.11756,
      "Crimstone": 0.67866667,
      "Leather": 0.14975,
      "Wool": 0.07219,
      "Merino Wool": 0.01399,
      "Feather": 0.009569,
      "Milk": 0.22611667,
      "Obsidian": 19.39,
      "Goblin Emblem": 0.058,
      "Bumpkin Emblem": 0.0845,
      "Sunflorian Emblem": 0.0615,
      "Nightshade Emblem": 0.0495,
      "Ruffroot": 0.7398,
      "Chewed Bone": 0.7522,
      "Heart Leaf": 0.7304,
      "Moonfur": 6.428,
      "Ribbon": 0.7218,
      "Dewberry": 0.86155,
      "Wild Grass": 0.7493,
      "Frost Pebble": 0.7442
    },
    "seq": {},
    "ge": {}
  },
  "updatedAt": 1775221211246,
  "updated_text": "a few seconds ago"
}